Pyl3sLib/__init__.py
Pyl3sLib/pyl3slib.py
Pyl3sLib-0.0.1.dist-info/LICENSE
Pyl3sLib-0.0.1.dist-info/METADATA
Pyl3sLib-0.0.1.dist-info/WHEEL
Pyl3sLib-0.0.1.dist-info/top_level.txt
Pyl3sLib-0.0.1.dist-info/RECORD
